apala_client/__init__.py
apala_client/client.py
apala_client/metadata.py
apala_client/models.py
apala_api-2.1.0.dist-info/METADATA
apala_api-2.1.0.dist-info/WHEEL
apala_api-2.1.0.dist-info/RECORD
