Metadata-Version: 2.4
Name: apala-api
Version: 2.1.0
Summary: Python SDK for Phoenix Message Analysis Services - Loan/Financial AI API Client
Author: Apala Cap
Keywords: ai,api,financial,loans,messaging,phoenix
Classifier: Development Status :: 4 - Beta
Classifier: Intended Audience :: Developers
Classifier: Programming Language :: Python :: 3
Classifier: Programming Language :: Python :: 3.9
Classifier: Programming Language :: Python :: 3.10
Classifier: Programming Language :: Python :: 3.11
Classifier: Programming Language :: Python :: 3.12
Classifier: Topic :: Office/Business :: Financial
Classifier: Topic :: Software Development :: Libraries :: Python Modules
Requires-Python: >=3.9
Requires-Dist: marimo>=0.16.5
Requires-Dist: pydantic!=2.10.0,!=2.10.1,!=2.10.2,!=2.10.3,<2.12,>=2.0
Requires-Dist: requests>=2.28.0
Provides-Extra: all
Requires-Dist: jupyter>=1.0.0; extra == 'all'
Requires-Dist: marimo>=0.3.0; extra == 'all'
Requires-Dist: mypy>=1.0.0; extra == 'all'
Requires-Dist: myst-parser>=3.0.1; extra == 'all'
Requires-Dist: pytest-cov>=4.0.0; extra == 'all'
Requires-Dist: pytest-mock>=3.10.0; extra == 'all'
Requires-Dist: pytest>=7.0.0; extra == 'all'
Requires-Dist: ruff>=0.1.0; extra == 'all'
Requires-Dist: sphinx-autodoc-typehints>=2.3.0; extra == 'all'
Requires-Dist: sphinx-rtd-theme>=3.0.2; extra == 'all'
Requires-Dist: sphinx>=7.4.7; extra == 'all'
Requires-Dist: tox>=4.0.0; extra == 'all'
Requires-Dist: types-requests>=2.28.0; extra == 'all'
Provides-Extra: dev
Requires-Dist: mypy>=1.0.0; extra == 'dev'
Requires-Dist: pytest-cov>=4.0.0; extra == 'dev'
Requires-Dist: pytest-mock>=3.10.0; extra == 'dev'
Requires-Dist: pytest>=7.0.0; extra == 'dev'
Requires-Dist: ruff>=0.1.0; extra == 'dev'
Requires-Dist: tox>=4.0.0; extra == 'dev'
Requires-Dist: types-requests>=2.28.0; extra == 'dev'
Provides-Extra: docs
Requires-Dist: myst-parser>=3.0.1; extra == 'docs'
Requires-Dist: sphinx-autodoc-typehints>=2.3.0; extra == 'docs'
Requires-Dist: sphinx-rtd-theme>=3.0.2; extra == 'docs'
Requires-Dist: sphinx>=7.4.7; extra == 'docs'
Provides-Extra: notebook
Requires-Dist: jupyter>=1.0.0; extra == 'notebook'
Requires-Dist: marimo>=0.3.0; extra == 'notebook'
